{
  "openapi": "3.0.1",
  "info": {
    "title": "BankingAPI",
    "version": "1.0"
  },
  "paths": {
    "/api/Account": {
      "post": {
        "tags": [
          "Account"
        ],
        "requestBody": {
          "content": {
            "application/json": {
              "schema": {
                "$ref": "#/components/schemas/CreateAccountRequest"
              }
            },
            "text/json": {
              "schema": {
                "$ref": "#/components/schemas/CreateAccountRequest"
              }
            },
            "application/*+json": {
              "schema": {
                "$ref": "#/components/schemas/CreateAccountRequest"
              }
            }
          }
        },
        "responses": {
          "200": {
            "description": "OK",
            "content": {
              "text/plain": {
                "schema": {
                  "$ref": "#/components/schemas/CreateAccountResponse"
                }
              },
              "application/json": {
                "schema": {
                  "$ref": "#/components/schemas/CreateAccountResponse"
                }
              },
              "text/json": {
                "schema": {
                  "$ref": "#/components/schemas/CreateAccountResponse"
                }
              }
            }
          }
        }
      },
      "get": {
        "tags": [
          "Account"
        ],
        "parameters": [
          {
            "name": "accountNumber",
            "in": "query",
            "schema": {
              "type": "string"
            }
          }
        ],
        "responses": {
          "200": {
            "description": "OK",
            "content": {
              "text/plain": {
                "schema": {
                  "$ref": "#/components/schemas/GetAccountResponse"
                }
              },
              "application/json": {
                "schema": {
                  "$ref": "#/components/schemas/GetAccountResponse"
                }
              },
              "text/json": {
                "schema": {
                  "$ref": "#/components/schemas/GetAccountResponse"
                }
              }
            }
          }
        }
      }
    }
  },
  "components": {
    "schemas": {
      "CreateAccountRequest": {
        "type": "object",
        "properties": {
          "balance": {
            "type": "number",
            "format": "float"
          },
          "accountType": {
            "type": "string",
            "nullable": true
          },
          "customerId": {
            "type": "integer",
            "format": "int32"
          }
        },
        "additionalProperties": false
      },
      "CreateAccountResponse": {
        "type": "object",
        "properties": {
          "accountNumber": {
            "type": "string",
            "nullable": true
          },
          "balance": {
            "type": "number",
            "format": "float"
          },
          "accountType": {
            "type": "string",
            "nullable": true
          },
          "customerId": {
            "type": "integer",
            "format": "int32"
          },
          "status": {
            "type": "string",
            "nullable": true
          }
        },
        "additionalProperties": false
      },
      "GetAccountResponse": {
        "type": "object",
        "properties": {
          "accountNumber": {
            "type": "string",
            "nullable": true
          },
          "balance": {
            "type": "number",
            "format": "float"
          },
          "accountType": {
            "type": "string",
            "nullable": true
          },
          "customerId": {
            "type": "integer",
            "format": "int32"
          },
          "status": {
            "type": "string",
            "nullable": true
          }
        },
        "additionalProperties": false
      }
    }
  }
}